LICENSE
MANIFEST.in
README.md
README.rst
setup.cfg
setup.py
blog/__init__.py
blog/admin.py
blog/apps.py
blog/models.py
blog/serializers.py
blog/tests.py
blog/urls.py
blog/views.py
blog/migrations/0001_initial.py
blog/migrations/__init__.py
drf_blog.egg-info/PKG-INFO
drf_blog.egg-info/SOURCES.txt
drf_blog.egg-info/dependency_links.txt
drf_blog.egg-info/requires.txt
drf_blog.egg-info/top_level.txt