Metadata-Version: 2.1
Name: drf-blog
Version: 1.0
Summary: A blog app for Django
Home-page: UNKNOWN
Author: HashTrust Technology
Author-email: vivek.sharma@hashTrust.in
License: MIT License
Platform: UNKNOWN
Classifier: Environment :: Web Environment
Classifier: Framework :: Django
Classifier: Intended Audience :: Developers
Classifier: License :: OSI Approved :: MIT License
Classifier: Operating System :: OS Independent
Classifier: Programming Language :: Python
Classifier: Programming Language :: Python :: 3
Classifier: Programming Language :: Python :: 3 :: Only
Classifier: Programming Language :: Python :: 3.9
Classifier: Programming Language :: Python :: 3.10
Classifier: Topic :: Communications :: Chat
Requires-Python: >=3.9
License-File: LICENSE
